{
  "events": [
    {
      "id": "14032",
      "title": "Inn Between Ride #1 — inner Southeast",
      "venue": "Holman's (aka Hello Inn)",
      "address": "15 SE 28th Ave, Portland, OR 97214",
      "organizer": "Josh",
      "details": "Ride bikes to bars named “inn,” or which are in inns, by way of in-between spaces. Not a loop, approximately 12 miles. Stops at: \r\n* Holman’s (aka Hello Inn)\r\n* Belmont Inn\r\n* Bear Paw Inn\r\n\r\nRoute map: https://ridewithgps.com/routes/55324020\r\n\r\nEnd time is approximate, but we'll probably get to the last stop around 9:00pm–9:30pm. The ride is free, but bring money for drinks and food. \r\n\r\nInn Between Rides are 3rd Mondays — see also ride #2 in July and #3 in August. \r\n\r\nIYBYB — If you're banned, you're banned. (Banned ride leaders and people banned from other rides need not attend.)",
      "time": "17:30:00",
      "hideemail": false,
      "hidephone": false,
      "hidecontact": false,
      "ridelength": "8-15",
      "timedetails": "Meet at 5:30pm, ride at 6:00pm",
      "locdetails": "Look for us on the patio",
      "loopride": false,
      "locend": "Bear Paw Inn, 3237 SE Milwaukie Ave, Portland, OR 97202",
      "eventduration": 270,
      "weburl": "https://mastodon.social/@press1forjosh",
      "webname": "@press1forjosh@mastodon.social",
      "image": null,
      "audience": "A",
      "tinytitle": "Inn Between Ride #1",
      "printdescr": "Bars named \"inn,\" or in an inn, via in-between spaces. Inner SE, ~12 mi; not a loop. Bring $ for drinks/food.",
      "datestype": "O",
      "area": "P",
      "featured": false,
      "printemail": true,
      "printphone": true,
      "printweburl": true,
      "printcontact": false,
      "published": true,
      "safetyplan": false,
      "email": "innbetweenride@joshuahetrick.info",
      "phone": "724-815-0434",
      "contact": "https://bit.ly/inn-between-ride-2026",
      "date": "2026-06-17",
      "caldaily_id": "24359",
      "shareable": "https://shift2bikes.org/calendar/event-24359",
      "exportable": "https://shift2bikes.org/api/ics.php?event_id=24359",
      "cancelled": false,
      "newsflash": "New date",
      "status": "A",
      "endtime": "22:00:00"
    }
  ]
}